Metadata-Version: 2.1
Name: ovos-tts-plugin-catotron
Version: 0.1.1
Summary: A catalan tacotron based tts plugin for mycroft
Home-page: https://github.com/OpenVoiceOS/ovos-tts-plugin-catotron
Author: JarbasAi
Author-email: jarbasai@mailfence.com
License: Apache-2.0
Keywords: mycroft ovos plugin tts
Platform: UNKNOWN
Classifier: Development Status :: 3 - Alpha
Classifier: Intended Audience :: Developers
Classifier: Topic :: Text Processing :: Linguistic
Classifier: License :: OSI Approved :: Apache Software License
Classifier: Programming Language :: Python :: 2
Classifier: Programming Language :: Python :: 2.7
Classifier: Programming Language :: Python :: 3
Classifier: Programming Language :: Python :: 3.0
Classifier: Programming Language :: Python :: 3.1
Classifier: Programming Language :: Python :: 3.2
Classifier: Programming Language :: Python :: 3.3
Classifier: Programming Language :: Python :: 3.4
Classifier: Programming Language :: Python :: 3.5
Classifier: Programming Language :: Python :: 3.6
